symdr/__init__.py
symdr/disc_waves.py
symdr/discrete_funcs.py
symdr/symdr.py
symdr/utils.py
symdr-1.0.3.dist-info/METADATA
symdr-1.0.3.dist-info/WHEEL
symdr-1.0.3.dist-info/top_level.txt
symdr-1.0.3.dist-info/RECORD
